tracelight/__init__.py
tracelight/agent_utils.py
tracelight/core.py
tracelight/decorators.py
tracelight-0.1.3.dist-info/licenses/LICENSE
tracelight-0.1.3.dist-info/METADATA
tracelight-0.1.3.dist-info/WHEEL
tracelight-0.1.3.dist-info/top_level.txt
tracelight-0.1.3.dist-info/RECORD
