Metadata-Version: 2.4
Name: tracelight
Version: 0.1.3
Summary: Reveal hidden state in Python exceptions with automatic variable tracing
Author-email: Your Actual Name <your.actual@email.com>
License: MIT
Project-URL: Homepage, https://github.com/newsbubbles/tracelight
Project-URL: Bug Tracker, https://github.com/newsbubbles/tracelight/issues
Project-URL: Documentation, https://github.com/newsbubbles/tracelight#readme
Keywords: debugging,exceptions,logging,tracing,agents
Classifier: Development Status :: 4 - Beta
Classifier: Intended Audience :: Developers
Classifier: License :: OSI Approved :: MIT License
Classifier: Programming Language :: Python :: 3
Classifier: Programming Language :: Python :: 3.7
Classifier: Programming Language :: Python :: 3.8
Classifier: Programming Language :: Python :: 3.9
Classifier: Programming Language :: Python :: 3.10
Classifier: Programming Language :: Python :: 3.11
Classifier: Topic :: Software Development :: Debuggers
Classifier: Topic :: Software Development :: Libraries :: Python Modules
Requires-Python: >=3.7
License-File: LICENSE
Dynamic: license-file
